stix_shifter_modules/error_test/__init__.py
stix_shifter_modules/error_test/entry_point.py
stix_shifter_modules/error_test/configuration/config.json
stix_shifter_modules/error_test/configuration/dialects.json
stix_shifter_modules/error_test/configuration/lang_en.json
stix_shifter_modules/error_test/stix_translation/__init__.py
stix_shifter_modules/error_test/stix_translation/json_to_stix_translator.py
stix_shifter_modules/error_test/stix_translation/query_translator.py
stix_shifter_modules/error_test/stix_translation/results_translator.py
stix_shifter_modules/error_test/stix_translation/two_queries_query_translator.py
stix_shifter_modules/error_test/stix_transmission/__init__.py
stix_shifter_modules/error_test/stix_transmission/connector.py
stix_shifter_modules_error_test-8.0.2.dist-info/licenses/AUTHORS.md
stix_shifter_modules_error_test-8.0.2.dist-info/licenses/LICENSE.md
stix_shifter_modules_error_test-8.0.2.dist-info/licenses/NOTICE
stix_shifter_modules_error_test-8.0.2.dist-info/METADATA
stix_shifter_modules_error_test-8.0.2.dist-info/WHEEL
stix_shifter_modules_error_test-8.0.2.dist-info/top_level.txt
stix_shifter_modules_error_test-8.0.2.dist-info/RECORD
